libfaketimefs_botocore/__init__.py
libfaketimefs_botocore/patch.py
libfaketimefs_botocore-0.0.2.dist-info/DESCRIPTION.rst
libfaketimefs_botocore-0.0.2.dist-info/METADATA
libfaketimefs_botocore-0.0.2.dist-info/RECORD
libfaketimefs_botocore-0.0.2.dist-info/WHEEL
libfaketimefs_botocore-0.0.2.dist-info/metadata.json
libfaketimefs_botocore-0.0.2.dist-info/top_level.txt
