Metadata-Version: 2.0
Name: libfaketimefs-botocore
Version: 0.0.2
Summary: Patches botocore to work with libfaketimefs
Home-page: https://github.com/claranet/libfaketimefs-botocore
Author: Raymond Butcher
Author-email: ray.butcher@claranet.uk
License: MIT License
Platform: UNKNOWN
Requires-Dist: botocore
